constructs/__init__.py
wulfmann_constructs-1.0.0.dist-info/METADATA
wulfmann_constructs-1.0.0.dist-info/WHEEL
wulfmann_constructs-1.0.0.dist-info/top_level.txt
wulfmann_constructs-1.0.0.dist-info/RECORD
